{
  "metadata": {
    "title": "Handi Chicken Curry - Authentic Indian Rajasthani Village Food Cooking Recipe - Primitive Style",
    "channel_name": "Sanjeev Kumar Gupta",
    "publish_date": "2019-07-01",
    "view_count": 81625,
    "like_count": 1273,
    "duration": "07:51",
    "original_audio_language": "Hindi",
    "video_id": "78dREYIqmBQ",
    "url": "https://www.youtube.com/watch?v=78dREYIqmBQ",
    "description": "This video shows authentic Rajasthani Handi Chicken cooked in a traditional village setting using a clay pot and mud stove in Ajmer, Rajasthan.",
    "ingredients_detected": [
      "chicken",
      "oil",
      "cinnamon",
      "mace",
      "cloves",
      "black pepper",
      "cardamom",
      "garlic",
      "cumin seeds",
      "bay leaf",
      "onion",
      "dry spices",
      "coriander powder",
      "turmeric powder"
    ]
  },

  "transcription_hindi": [
    "[00:00:00.000] दोस्तों, इस वीडियो में हम आपको राजस्थान की प्रसिद्ध हांडी चिकन मसाला दिखाने जा रहे हैं।",
    "[00:00:06.000] जिसे एक राजस्थानी गांव की महिला मिट्टी की हांडी में बना रही है।",
    "[00:00:14.000] इस तरह से बना हुआ खाना बहुत ही कम देखने को मिलता है, वीडियो को अंत तक देखिए।",
    "[00:00:20.000] दालचीनी, जावित्री, लौंग, काली मिर्च, इलायची, लहसुन।",
    "[00:01:09.000] जीरा, जीरा, जीरा।",
    "[00:01:50.000] इस वीडियो में हम आपको राजस्थान की प्रसिद्ध हांडी चिकन मसाला दिखा रहे हैं।",
    "[00:01:55.000] जिसे एक गांव की महिला मिट्टी की हांडी में बना रही है।",
    "[00:01:58.000] यह पारंपरिक राजस्थानी स्वाद का बेहतरीन उदाहरण है।",
    "[00:02:31.000] यह बहुत स्वादिष्ट बनता है।",
    "[00:02:37.000] सर्दियों में कौन-कौन सी मिठाइयाँ बनती हैं?",
    "[00:02:40.000] मेथी का लड्डू।",
    "[00:02:43.000] मेथी का लड्डू।",
    "[00:02:44.000] उड़द का लड्डू।",
    "[00:02:54.000] यह तैयार हो गया है।",
    "[00:02:57.000] हां, यह तैयार है।",
    "[00:03:02.000] तेज पत्ता।",
    "[00:04:54.000] दालचीनी।",
    "[00:04:56.000] प्याज़।",
    "[00:05:45.000] मसाला।",
    "[00:05:47.000] सूखे मसाले।",
    "[00:06:00.000] धनिया और हल्दी।",
    "[00:07:00.000] यह बहुत ही स्वादिष्ट है।"
  ],

  "transcription_english": [
    "[00:00:00.000] Friends, in this video we are going to show you Rajasthan's famous handi chicken masala.",
    "[00:00:06.000] Which is being cooked by a village woman in a clay pot.",
    "[00:00:14.000] It is very rare to see food cooked in this traditional way, watch till the end.",
    "[00:00:20.000] Cinnamon, mace, cloves, black pepper, cardamom, garlic.",
    "[00:01:09.000] Cumin seeds, cumin seeds, cumin seeds.",
    "[00:01:50.000] In this video we are showing Rajasthan's famous handi chicken masala.",
    "[00:01:55.000] Which is cooked by a village woman using a clay pot.",
    "[00:01:58.000] This is a fine example of traditional Rajasthani taste.",
    "[00:02:31.000] It is very tasty.",
    "[00:02:37.000] Which sweets are made in winter?",
    "[00:02:40.000] Fenugreek ladoo.",
    "[00:02:43.000] Fenugreek ladoo.",
    "[00:02:44.000] Urad ladoo.",
    "[00:02:54.000] It is ready.",
    "[00:02:57.000] Yes, it is ready.",
    "[00:03:02.000] Bay leaf.",
    "[00:04:54.000] Cinnamon.",
    "[00:04:56.000] Onion.",
    "[00:05:45.000] Masala.",
    "[00:05:47.000] Dry spices.",
    "[00:06:00.000] Coriander and turmeric.",
    "[00:07:00.000] It is very tasty."
  ]
}
